tickertick/__init__.py
tickertick/query.py
pytickertick-1.0.0.dist-info/METADATA
pytickertick-1.0.0.dist-info/WHEEL
pytickertick-1.0.0.dist-info/top_level.txt
pytickertick-1.0.0.dist-info/RECORD
