Metadata-Version: 2.1
Name: pytickertick
Version: 1.0.0
Summary: An API wrapper for the TickerTick API in Python
Author: pennacap
Project-URL: Homepage, https://github.com/pennacap/pytickertick
Project-URL: Bug Tracker, https://github.com/pennacap/pytickertick/issues
Classifier: Programming Language :: Python :: 3
Classifier: License :: OSI Approved :: MIT License
Classifier: Operating System :: OS Independent
Requires-Python: >=3.6
